CHANGES.txt
DEPENDENCIES.txt
README.txt
bootstrap.py
buildout.cfg
setup.py
src/ks/__init__.py
src/ks.installtool.egg-info/PKG-INFO
src/ks.installtool.egg-info/SOURCES.txt
src/ks.installtool.egg-info/dependency_links.txt
src/ks.installtool.egg-info/namespace_packages.txt
src/ks.installtool.egg-info/not-zip-safe
src/ks.installtool.egg-info/requires.txt
src/ks.installtool.egg-info/top_level.txt
src/ks/installtool/INSTALL.txt
src/ks/installtool/LICENSE.txt
src/ks/installtool/README.ru.txt
src/ks/installtool/TODO.txt
src/ks/installtool/__init__.py
src/ks/installtool/configure.zcml
src/ks/installtool/exceptions.py
src/ks/installtool/factories.py
src/ks/installtool/installtool-proposal.txt
src/ks/installtool/installtool.txt
src/ks/installtool/installtool_doc.txt
src/ks/installtool/interfaces.py
src/ks/installtool/demo/README.txt
src/ks/installtool/demo/__init__.py
src/ks/installtool/demo/add.py
src/ks/installtool/demo/appendix3.py
src/ks/installtool/demo/configure.zcml
src/ks/installtool/demo/interfaces.py
src/ks/installtool/demo/scripts.py
src/ks/installtool/demo/etc/installtool-configure.zcml
src/ks/installtool/etc/installtool-configure.zcml
src/ks/installtool/etc/zcmlfactoryform-meta.zcml
src/ks/installtool/etc/zcmlinstall-meta.zcml
src/ks/installtool/etc/zcmlscript-meta.zcml
src/ks/installtool/factory/__init__.py
src/ks/installtool/factory/configure.zcml
src/ks/installtool/factory/factory.py
src/ks/installtool/factory/factory.txt
src/ks/installtool/factory/browser/__init__.py
src/ks/installtool/factory/browser/configure.zcml
src/ks/installtool/factory/browser/deps_error.pt
src/ks/installtool/factory/browser/runtime_error.pt
src/ks/installtool/factory/browser/runtimeerrorview.py
src/ks/installtool/factory/browser/unknown_deps.pt
src/ks/installtool/factory/browser/unresolvederrorview.py
src/ks/installtool/installerregistry/__init__.py
src/ks/installtool/installerregistry/configure.zcml
src/ks/installtool/installerregistry/installerregistry.py
src/ks/installtool/installerregistry/installerregistry.txt
src/ks/installtool/installerregistry/interfaces.py
src/ks/installtool/installscript/__init__.py
src/ks/installtool/installscript/configure.zcml
src/ks/installtool/installscript/installscript.py
src/ks/installtool/installscript/installscript.txt
